textura/__init__.py
textura/textura.py
textura-1.1.0.dist-info/licenses/LICENSE
textura-1.1.0.dist-info/METADATA
textura-1.1.0.dist-info/WHEEL
textura-1.1.0.dist-info/top_level.txt
textura-1.1.0.dist-info/RECORD
